evtx2pandas/__init__.py
evtx2pandas/json_to_csv.py
evtx2pandas-0.0.4.dist-info/COPYING
evtx2pandas-0.0.4.dist-info/METADATA
evtx2pandas-0.0.4.dist-info/WHEEL
evtx2pandas-0.0.4.dist-info/top_level.txt
evtx2pandas-0.0.4.dist-info/RECORD
