Metadata-Version: 2.1
Name: evtx2pandas
Version: 0.0.4
Summary: Convert EVTX to pandas DataFrame.
Home-page: https://github.com/thibaultbl/evtx2pandas
Author: Thibault Blanc
Author-email: UNKNOWN
License: GNU General Public License
Keywords: evtx pandas Event logs
Platform: UNKNOWN
Classifier: Development Status :: 3 - Alpha
Classifier: Topic :: Utilities
Classifier: License :: OSI Approved :: GNU General Public License v2 or later (GPLv2+)
Classifier: Intended Audience :: Developers
Classifier: Natural Language :: English
Classifier: Operating System :: Unix
Classifier: Programming Language :: Python
Classifier: Programming Language :: Python :: 3
Classifier: Programming Language :: Python :: 3.5
Classifier: Programming Language :: Python :: 3.6
Classifier: Programming Language :: Python :: 3.7
Classifier: Programming Language :: Python :: 3.8
Classifier: Programming Language :: Python :: 3.9
Classifier: Topic :: Software Development :: Libraries :: Python Modules
Classifier: Topic :: Scientific/Engineering
Requires-Dist: dask (>=2021.12.0)
Requires-Dist: evtx (>=0.6.11)
Requires-Dist: pandas (>=1.3.5)
Requires-Dist: pytest (>=6.2.5)
